README.md
setup.py
kfp/dsl/__init__.py
kfp/dsl/base_component.py
kfp/dsl/component_decorator.py
kfp/dsl/component_factory.py
kfp/dsl/constants.py
kfp/dsl/container_component_artifact_channel.py
kfp/dsl/container_component_class.py
kfp/dsl/container_component_decorator.py
kfp/dsl/executor.py
kfp/dsl/executor_main.py
kfp/dsl/for_loop.py
kfp/dsl/graph_component.py
kfp/dsl/importer_component.py
kfp/dsl/importer_node.py
kfp/dsl/kfp_config.py
kfp/dsl/pipeline_channel.py
kfp/dsl/pipeline_context.py
kfp/dsl/pipeline_task.py
kfp/dsl/placeholders.py
kfp/dsl/python_component.py
kfp/dsl/structures.py
kfp/dsl/task_final_status.py
kfp/dsl/tasks_group.py
kfp/dsl/utils.py
kfp/dsl/v1_modelbase.py
kfp/dsl/v1_structures.py
kfp/dsl/yaml_component.py
kfp/dsl/types/__init__.py
kfp/dsl/types/artifact_types.py
kfp/dsl/types/custom_artifact_types.py
kfp/dsl/types/type_annotations.py
kfp/dsl/types/type_utils.py
kfp_dsl.egg-info/PKG-INFO
kfp_dsl.egg-info/SOURCES.txt
kfp_dsl.egg-info/dependency_links.txt
kfp_dsl.egg-info/requires.txt
kfp_dsl.egg-info/top_level.txt