Metadata-Version: 1.2
Name: kfp-dsl
Version: 2.1.1
Summary: A KFP SDK subpackage containing the DSL and runtime code.
Home-page: https://github.com/kubeflow/pipelines
Author: google
Author-email: kubeflow-pipelines@google.com
License: Apache 2.0
Platform: UNKNOWN
Requires-Python: >=3.7.0
